pipelinenotifier/__init__.py
pipelinenotifier/base.py
pipelinenotifier/discord.py
pipelinenotifier/keybase.py
pipelinenotifier/slack.py
pipeline_notifier-0.0.2.dist-info/LICENSE
pipeline_notifier-0.0.2.dist-info/METADATA
pipeline_notifier-0.0.2.dist-info/WHEEL
pipeline_notifier-0.0.2.dist-info/top_level.txt
pipeline_notifier-0.0.2.dist-info/RECORD
