Metadata-Version: 2.1
Name: pipeline-notifier
Version: 0.0.2
Summary: A small example package
Home-page: https://github.com/boba-and-beer/pipelinenotifier
Author: Jacky Wong
Author-email: jacky.wong@vctr.ai
License: UNKNOWN
Platform: UNKNOWN
Classifier: Programming Language :: Python :: 3
Classifier: License :: OSI Approved :: MIT License
Classifier: Operating System :: OS Independent
Requires-Python: >=3.6
